<?xml version="1.0" encoding="utf-8" ?>
<dwsync>
<file name="document_bg.jpg" server="C:/wamp/www/survey-project/" local="130244797063076167" remote="130244797060000000" />
<file name="favicon.ico" server="C:/wamp/www/survey-project/" local="130244797063106169" remote="130244797060000000" />
<file name="header_bg.jpg" server="C:/wamp/www/survey-project/" local="130244797063166172" remote="130244797060000000" />
<file name="bullet.png" server="C:/wamp/www/survey-project/" local="130246752741638849" remote="130246752740000000" />
<file name="report-box-bg.png" server="C:/wamp/www/survey-project/" local="130245791081833200" remote="130245791080000000" />
<file name="se-save.gif" server="C:/wamp/www/survey-project/" local="130244083243701520" remote="130244083240000000" />
<file name="ico-move.png" server="C:/wamp/www/survey-project/" local="130244083267452879" remote="130244083260000000" />
<file name="bullet copy.png" server="C:/wamp/www/survey-project/" local="130246752599480718" remote="130246752590000000" />
<file name="clip_1.jpg" server="C:/wamp/www/survey-project/" local="130244797062576138" remote="130244797060000000" />
<file name="dialog-load.gif" server="C:/wamp/www/survey-project/" local="130244083274123260" remote="130244083270000000" />
<file name="form-radio.png" server="C:/wamp/www/survey-project/" local="130244083247791754" remote="130244083240000000" />
<file name="q-number-bg.png" server="C:/wamp/www/survey-project/" local="130244083246121659" remote="130244083240000000" />
<file name="quiz-incorrect.png" server="C:/wamp/www/survey-project/" local="130244083263542655" remote="130244083260000000" />
</dwsync>